MANIFEST.in
README.md
requirements.txt
setup.cfg
setup.py
gqblog/__init__.py
gqblog/app.py
gqblog/utils.py
gqblog.egg-info/PKG-INFO
gqblog.egg-info/SOURCES.txt
gqblog.egg-info/dependency_links.txt
gqblog.egg-info/entry_points.txt
gqblog.egg-info/requires.txt
gqblog.egg-info/top_level.txt
gqblog/blog/__init__.py
gqblog/blog/fixtures.py
gqblog/blog/schema.py