Metadata-Version: 1.1
Name: gqblog
Version: 0.0.1
Summary: A blog demo use graphql
Home-page: https://github.com/youngking/gqblog
Author: Young King
Author-email: yanckin@gmail.com
License: BSD
Download-URL: https://github.com/youngking/gqblog/tarball/0.0.1
Platform: UNKNOWN
Classifier: Development Status :: 3 - Alpha
Classifier: Intended Audience :: Developers
Classifier: Programming Language :: Python :: 3
